grpc_status-stubs/METADATA.toml
grpc_status-stubs/__init__.pyi
grpc_status-stubs/_async.pyi
grpc_status-stubs/py.typed
grpc_status-stubs/rpc_status.pyi
types_grpcio_status-1.0.0.20250506.dist-info/licenses/LICENSE
types_grpcio_status-1.0.0.20250506.dist-info/METADATA
types_grpcio_status-1.0.0.20250506.dist-info/WHEEL
types_grpcio_status-1.0.0.20250506.dist-info/top_level.txt
types_grpcio_status-1.0.0.20250506.dist-info/RECORD
